django_ogcapif/__init__.py
django_ogcapif/__version__.py
django_ogcapif/decorators.py
django_ogcapif/filters.py
django_ogcapif/mixins.py
django_ogcapif/pagination.py
django_ogcapif/parsers.py
django_ogcapif/routers.py
django_ogcapif/urls.py
django_ogcapif/views.py
django_ogcapif-0.1.6.dist-info/LICENSE
django_ogcapif-0.1.6.dist-info/METADATA
django_ogcapif-0.1.6.dist-info/WHEEL
django_ogcapif-0.1.6.dist-info/top_level.txt
django_ogcapif-0.1.6.dist-info/RECORD
