Metadata-Version: 2.1
Name: django-ogcapif
Version: 0.1.6
Summary: Easily expose your Django models through an OGCAPI-Features endpoint
Author-email: "OPENGIS.ch" <info@opengis.ch>
License: MIT License
Project-URL: homepage, https://github.com/opengisch/django-ogcapif
Project-URL: repository, https://github.com/opengisch/django-ogcapif
Project-URL: tracker, https://github.com/opengisch/django-ogcapif/issues
Keywords: django,ogc,api,wfs3,features,rest,gis,ogcapif
Classifier: Framework :: Django
Classifier: Intended Audience :: Developers
Classifier: Programming Language :: Python :: 3
Classifier: Topic :: Scientific/Engineering :: GIS
License-File: LICENSE
Requires-Dist: django (>=4)
Requires-Dist: django-computedfields
Requires-Dist: psycopg2
Requires-Dist: transifex-client
Requires-Dist: djangorestframework
Requires-Dist: djangorestframework-gis
Requires-Dist: pyyaml
Requires-Dist: uritemplate
Requires-Dist: pyproj
Provides-Extra: dev
Requires-Dist: pre-commit ; extra == 'dev'
Requires-Dist: debugpy ; extra == 'dev'
Requires-Dist: django-debug-toolbar ; extra == 'dev'
Requires-Dist: flameprof ; extra == 'dev'
Requires-Dist: gprof2dot ; extra == 'dev'
